<?xml version="1.0" encoding="utf-8"?>
<key id="b83793c0-a67a-4a0b-b24b-9a78bcf772b5" version="1">
  <creationDate>2020-03-21T22:51:23.3795944Z</creationDate>
  <activationDate>2020-03-21T22:51:23.3772121Z</activationDate>
  <expirationDate>2020-06-19T22:51:23.3772121Z</expirationDate>
  <descriptor deserializerType="Microsoft.AspNetCore.DataProtection.AuthenticatedEncryption.ConfigurationModel.AuthenticatedEncryptorDescriptorDeserializer, Microsoft.AspNetCore.DataProtection, Version=3.1.1.0, Culture=neutral, PublicKeyToken=adb9793829ddae60">
    <descriptor>
      <encryption algorithm="AES_256_CBC" />
      <validation algorithm="HMACSHA256" />
      <masterKey p4:requiresEncryption="true" xmlns:p4="http://schemas.asp.net/2015/03/dataProtection">
        <!-- Warning: the key below is in an unencrypted form. -->
        <value>KdBAChFMMNLPMzR3yErIz5zqovwOkFbXt0yug9AJWk3ArllLkUbkzQI5U+c2oQa6PTSrUgC4pZi5TItpwmHW+A==</value>
      </masterKey>
    </descriptor>
  </descriptor>
</key>